[
  {
    "id": "vetfarm-derm-shampoo",
    "name": "Vetfarm Derm Shampoo",
    "description": "Shampoo dermatológico medicado para el tratamiento de dermatitis, piodermas y afecciones cutáneas en perros. Fórmula con clorhexidina y ketoconazol.",
    "image": "https://images.unsplash.com/photo-1587300003388-59208cc962cb?w=600&q=80&auto=format",
    "category": "canino",
    "species": "Canino (Perros)",
    "featured": true,
    "presentations": [
      { "size": "120 ml", "price": 185 },
      { "size": "250 ml", "price": 310 },
      { "size": "500 ml", "price": 520 }
    ]
  },
  {
    "id": "vetfarm-artro-flex",
    "name": "Vetfarm Artro Flex",
    "description": "Suplemento articular con glucosamina, condroitina y MSM para el soporte de articulaciones en perros adultos y geriátricos.",
    "image": "https://images.unsplash.com/photo-1558788353-f76d92427f16?w=600&q=80&auto=format",
    "category": "canino",
    "species": "Canino (Perros)",
    "featured": true,
    "presentations": [
      { "size": "30 tabletas", "price": 290 },
      { "size": "60 tabletas", "price": 480 },
      { "size": "90 tabletas", "price": 650 }
    ]
  },
  {
    "id": "vetfarm-parasit-oral",
    "name": "Vetfarm Parasit Oral",
    "description": "Antiparasitario oral de amplio espectro para el control de parásitos internos en caninos. Acción rápida y efectiva contra nematodos y cestodos.",
    "image": "https://images.unsplash.com/photo-1587764379873-97837921fd44?w=600&q=80&auto=format",
    "category": "canino",
    "species": "Canino (Perros)",
    "featured": false,
    "presentations": [
      { "size": "1 tableta (perro pequeño)", "price": 85 },
      { "size": "1 tableta (perro mediano)", "price": 120 },
      { "size": "1 tableta (perro grande)", "price": 160 }
    ]
  },
  {
    "id": "vetfarm-otic-clean",
    "name": "Vetfarm Otic Clean",
    "description": "Solución ótica limpiadora y desinfectante para la higiene del canal auditivo en perros. Previene otitis y elimina cerumen.",
    "image": "https://images.unsplash.com/photo-1601758228041-f3b2795255f1?w=600&q=80&auto=format",
    "category": "canino",
    "species": "Canino (Perros)",
    "featured": false,
    "presentations": [
      { "size": "60 ml", "price": 145 },
      { "size": "120 ml", "price": 235 }
    ]
  },
  {
    "id": "vetfarm-feline-vitapel",
    "name": "Vetfarm Feline VitaPel",
    "description": "Suplemento vitamínico para piel y pelaje de gatos. Con biotina, omega 3 y 6, zinc y vitamina E para un pelaje brillante y saludable.",
    "image": "https://images.unsplash.com/photo-1574158622682-e40e69881006?w=600&q=80&auto=format",
    "category": "felino",
    "species": "Felino (Gatos)",
    "featured": true,
    "presentations": [
      { "size": "30 ml (gotero)", "price": 175 },
      { "size": "60 ml (gotero)", "price": 290 }
    ]
  },
  {
    "id": "vetfarm-feline-calm",
    "name": "Vetfarm Feline Calm",
    "description": "Suplemento ansiolítico natural para gatos. Reduce el estrés y la ansiedad en situaciones como mudanzas, viajes o visitas al veterinario.",
    "image": "https://images.unsplash.com/photo-1526336024174-e58f5cdd8e13?w=600&q=80&auto=format",
    "category": "felino",
    "species": "Felino (Gatos)",
    "featured": false,
    "presentations": [
      { "size": "20 tabletas", "price": 210 },
      { "size": "40 tabletas", "price": 365 }
    ]
  },
  {
    "id": "vetfarm-feline-parasit",
    "name": "Vetfarm Feline Parasit",
    "description": "Antiparasitario interno formulado específicamente para gatos. Acción contra parásitos redondos y planos con dosis precisa por peso.",
    "image": "https://images.unsplash.com/photo-1495360010541-f48722b34f7d?w=600&q=80&auto=format",
    "category": "felino",
    "species": "Felino (Gatos)",
    "featured": false,
    "presentations": [
      { "size": "1 tableta (gato pequeño)", "price": 75 },
      { "size": "1 tableta (gato adulto)", "price": 95 }
    ]
  },
  {
    "id": "vetfarm-avi-electro",
    "name": "Vetfarm Avi Electro",
    "description": "Electrolitos y vitaminas hidrosolubles para aves de producción. Previene deshidratación y estrés calórico. Uso en agua de bebida.",
    "image": "https://images.unsplash.com/photo-1548550023-2bdb3c5beed7?w=600&q=80&auto=format",
    "category": "aves",
    "species": "Aves",
    "featured": true,
    "presentations": [
      { "size": "100 g", "price": 95 },
      { "size": "500 g", "price": 350 },
      { "size": "1 kg", "price": 580 }
    ]
  },
  {
    "id": "vetfarm-avi-respira",
    "name": "Vetfarm Avi Respira",
    "description": "Tratamiento respiratorio para aves. Combinación antibiótica para el control de enfermedades respiratorias crónicas y micoplasmosis aviar.",
    "image": "https://images.unsplash.com/photo-1612170153139-6f881ff067e0?w=600&q=80&auto=format",
    "category": "aves",
    "species": "Aves",
    "featured": false,
    "presentations": [
      { "size": "100 ml", "price": 165 },
      { "size": "250 ml", "price": 320 },
      { "size": "1 litro", "price": 890 }
    ]
  },
  {
    "id": "vetfarm-avi-hepato",
    "name": "Vetfarm Avi Hepato",
    "description": "Protector hepático para aves de producción. Estimula la función del hígado y mejora el metabolismo durante periodos de alta producción.",
    "image": "https://images.unsplash.com/photo-1569396116180-210c182bedb8?w=600&q=80&auto=format",
    "category": "aves",
    "species": "Aves",
    "featured": false,
    "presentations": [
      { "size": "250 ml", "price": 210 },
      { "size": "1 litro", "price": 650 }
    ]
  }
]
